github_readme_stats/__init__.py
github_readme_stats/exceptions.py
github_readme_stats/github_stats.py
github_readme_stats/readme_updater.py
github_readme_stats-0.1.1.dist-info/LICENSE
github_readme_stats-0.1.1.dist-info/METADATA
github_readme_stats-0.1.1.dist-info/WHEEL
github_readme_stats-0.1.1.dist-info/top_level.txt
github_readme_stats-0.1.1.dist-info/RECORD
