Metadata-Version: 2.1
Name: github-readme-stats
Version: 0.1.1
Summary: Automatically update your GitHub README with your latest GitHub statistics
Home-page: https://github.com/ascender1729/github-readme-stats
Author: Dubasi Pavan Kumar
Author-email: pavan.dubasi2024@gmail.com
Classifier: Development Status :: 3 - Alpha
Classifier: Intended Audience :: Developers
Classifier: License :: OSI Approved :: MIT License
Classifier: Operating System :: OS Independent
Classifier: Programming Language :: Python :: 3
Classifier: Programming Language :: Python :: 3.7
Classifier: Programming Language :: Python :: 3.8
Classifier: Programming Language :: Python :: 3.9
Requires-Python: >=3.7
License-File: LICENSE
Requires-Dist: PyGithub >=1.55
Requires-Dist: python-dotenv >=0.19.0
